LycorisQ.py
LycorisQ-1.0.18.dist-info/LICENSE
LycorisQ-1.0.18.dist-info/METADATA
LycorisQ-1.0.18.dist-info/WHEEL
LycorisQ-1.0.18.dist-info/top_level.txt
LycorisQ-1.0.18.dist-info/RECORD
