Metadata-Version: 2.1
Name: LycorisQ
Version: 1.0.18
Summary: A neat reinforcement learning framework based on LycorisNet.
Home-page: https://github.com/RootHarold/LycorisQ
Author: RootHarold
Author-email: rootharold@163.com
License: UNKNOWN
Platform: UNKNOWN
Requires-Dist: LycorisNet (>=2.5)
Requires-Dist: numpy (>=1.18)
